LICENSE
MANIFEST.in
README.rst
pyproject.toml
setup.cfg
setup.py
nut2/__init__.py
nut2/nut2_old.py
ph4_nut2.egg-info/PKG-INFO
ph4_nut2.egg-info/SOURCES.txt
ph4_nut2.egg-info/dependency_links.txt
ph4_nut2.egg-info/requires.txt
ph4_nut2.egg-info/top_level.txt
tests/test_client.py
tests/test_client2.py
tests/test_nutclient.py