Metadata-Version: 2.1
Name: ph4-nut2
Version: 3.1.0
Summary: A Python abstraction class to access NUT servers.
Home-page: https://github.com/ph4r05/python-nut2
Author: Ryan Shipp, Dusan Klinec
Author-email: python@rshipp.com, ph4r05@gmail.com
License: GPL3
Classifier: Intended Audience :: Developers
Classifier: Intended Audience :: Information Technology
Classifier: Intended Audience :: System Administrators
Classifier: License :: OSI Approved :: GNU General Public License v3 or later (GPLv3+)
Classifier: Operating System :: OS Independent
Classifier: Programming Language :: Python
Classifier: Programming Language :: Python :: 3
Classifier: Topic :: Software Development :: Libraries
Classifier: Topic :: System :: Power (UPS)
Classifier: Topic :: System :: Systems Administration
License-File: LICENSE
Requires-Dist: telnetlib3>=2.0.4
